ygg_torrent/__init__.py
ygg_torrent/__main__.py
ygg_torrent/fastapi_server.py
ygg_torrent/mcp_server.py
ygg_torrent/test_mcp_server.py
ygg_torrent/wrapper/__init__.py
ygg_torrent/wrapper/api_client.py
ygg_torrent/wrapper/categories.py
ygg_torrent/wrapper/models.py
ygg_torrent/wrapper/torrent_editor.py
ygg_torrent/wrapper/utils.py
ygg_torrent_mcp_fastmcp-1.8.2.dist-info/METADATA
ygg_torrent_mcp_fastmcp-1.8.2.dist-info/WHEEL
ygg_torrent_mcp_fastmcp-1.8.2.dist-info/entry_points.txt
ygg_torrent_mcp_fastmcp-1.8.2.dist-info/licenses/LICENSE
ygg_torrent_mcp_fastmcp-1.8.2.dist-info/RECORD
