Metadata-Version: 2.4
Name: ygg-torrent-mcp-fastmcp
Version: 1.8.2
Summary: Ygg Torrent MCP Server
Project-URL: Homepage, https://github.com/fastmcp-me/ygg-torrent-mcp#readme
Project-URL: Repository, https://github.com/fastmcp-me/ygg-torrent-mcp.git
Project-URL: Issues, https://github.com/fastmcp-me/ygg-torrent-mcp/issues
Author: philogicae
License-Expression: MIT
License-File: LICENSE
Requires-Python: <4.0,>=3.10
Requires-Dist: bencodepy
Requires-Dist: fastapi
Requires-Dist: fastmcp
Requires-Dist: requests
